scaffo/__init__.py
scaffo/agent_base.py
scaffo/gym_runner.py
scaffo-0.0.2.dist-info/METADATA
scaffo-0.0.2.dist-info/WHEEL
scaffo-0.0.2.dist-info/top_level.txt
scaffo-0.0.2.dist-info/RECORD
