Metadata-Version: 2.1
Name: scaffo
Version: 0.0.2
Summary: A framework to make creating AI agents easier
Home-page: http://www.ryanjames.io
Author: Ryan McCauley
Author-email: ryanmccauley211@gmail.com
License: UNKNOWN
Platform: UNKNOWN
